venv_retarget/__init__.py
venv_retarget/__main__.py
venv_retarget/defs.py
venv_retarget/detect.py
venv_retarget/impl.py
venv_retarget/py.typed
venv_retarget/util.py
venv_retarget-0.1.1.dist-info/METADATA
venv_retarget-0.1.1.dist-info/WHEEL
venv_retarget-0.1.1.dist-info/entry_points.txt
venv_retarget-0.1.1.dist-info/licenses/LICENSES/BSD-2-Clause.txt
venv_retarget-0.1.1.dist-info/RECORD
