Metadata-Version: 2.4
Name: venv-retarget
Version: 0.1.1
Summary: Prepare a virtual environment for moving to another directory
Project-URL: Homepage, https://devel.ringlet.net/sysutils/venv-retarget/
Project-URL: Changes, https://devel.ringlet.net/sysutils/venv-retarget/changes/
Project-URL: Issue Tracker, https://gitlab.com/ppentchev/venv-retarget/-/issues
Project-URL: Source Code, https://gitlab.com/ppentchev/venv-retarget
Author-email: Peter Pentchev <roam@ringlet.net>
License-Expression: BSD-2-Clause
License-File: LICENSES/BSD-2-Clause.txt
Classifier: Development Status :: 3 - Alpha
Classifier: Environment :: Console
Classifier: Intended Audience :: Developers
Classifier: Intended Audience :: System Administrators
Classifier: Operating System :: POSIX
Classifier: Programming Language :: Python
Classifier: Programming Language :: Python :: 3
Classifier: Programming Language :: Python :: 3 :: Only
Classifier: Programming Language :: Python :: 3.11
Classifier: Programming Language :: Python :: 3.12
Classifier: Programming Language :: Python :: 3.13
Classifier: Programming Language :: Python :: 3.14
Classifier: Topic :: Software Development :: Libraries
Classifier: Topic :: Software Development :: Libraries :: Python Modules
Classifier: Topic :: System :: Filesystems
Classifier: Topic :: System :: Installation/Setup
Classifier: Topic :: System :: Software Distribution
Classifier: Topic :: Utilities
Classifier: Typing :: Typed
Requires-Python: >=3.11
Requires-Dist: click<9,>=8
